{
  "1": [
    {
      "title": "스타 II PIG 대회",
      "time": "6PM",
      "color": "#34F5D8",
      "link": ""
    }
  ],
  "2": [
    {
      "title": "89모임 김나성 방송",
      "time": "7PM",
      "color": "#FFC857",
      "link": ""
    }
  ],
  "3": [
    {
      "title": "바이오하자드 9",
      "time": "",
      "color": "#FFC857",
      "link": ""
    }
  ],
  "4": [
    {
      "title": "바이오하자드 9",
      "time": "",
      "color": "#FFC857",
      "link": ""
    }
  ],
  "5": [
    {
      "title": "삼성 vs 한화 연습 경기",
      "time": "1PM",
      "color": "#A56BFF",
      "link": ""
    },
    {
      "title": "포코피아",
      "time": "",
      "color": "#FFC857",
      "link": ""
    }
  ],
  "6": [
    {
      "title": "알라바스타 던",
      "time": "",
      "color": "#34F5D8",
      "link": ""
    },
    {
      "title": "허 트리즈",
      "time": "",
      "color": "#FFC857",
      "link": ""
    },
    {
      "title": "롤",
      "time": "",
      "color": "#FFC857",
      "link": ""
    }
  ],
  "7": [
    {
      "title": "삼성 vs KT 연습 경기",
      "time": "1PM",
      "color": "#A56BFF",
      "link": ""
    },
    {
      "title": "스타 II RSL 박한솔 입중계 응원",
      "time": "7PM",
      "color": "#34F5D8",
      "link": ""
    }
  ],
  "8": [
    {
      "title": "허츄님과 스타 1 핸디캡 매치",
      "time": "",
      "color": "#34F5D8",
      "link": ""
    }
  ],
  "9": [
    {
      "title": "롤",
      "time": "",
      "color": "#FFC857",
      "link": ""
    }
  ],
  "10": [
    {
      "title": "휴방",
      "time": "",
      "color": "#FF4D6D",
      "link": ""
    }
  ],
  "11": [
    {
      "title": "올리비아 여행 출국",
      "time": "",
      "color": "#FFC857",
      "link": ""
    },
    {
      "title": "스타 II Wardi 팀리그",
      "time": "9PM",
      "color": "#34F5D8",
      "link": ""
    },
    {
      "title": "롤",
      "time": "",
      "color": "#FFC857",
      "link": ""
    }
  ],
  "12": [
    {
      "title": "스타 II Wardi 팀리그",
      "time": "9PM",
      "color": "#34F5D8",
      "link": ""
    },
    {
      "title": "ONSYDE 경기",
      "time": "",
      "color": "#FFC857",
      "link": ""
    }
  ],
  "13": [
    {
      "title": "매직박형님과 롤 북벌",
      "time": "",
      "color": "#FFC857",
      "link": ""
    }
  ],
  "14": [
    {
      "title": "낙원, 헤일로",
      "time": "",
      "color": "#FFC857",
      "link": ""
    }
  ],
  "15": [
    {
      "title": "스타 II RSL 조성주 입중계 응원",
      "time": "7PM",
      "color": "#34F5D8",
      "link": ""
    },
    {
      "title": "스타 II Wardi 팀리그",
      "time": "10PM",
      "color": "#34F5D8",
      "link": ""
    }
  ],
  "16": [
    {
      "title": "롤",
      "time": "",
      "color": "#FFC857",
      "link": ""
    }
  ],
  "17": [
    {
      "title": "스타 II Wardi 팀리그",
      "time": "10PM",
      "color": "#34F5D8",
      "link": ""
    },
    {
      "title": "ONSYDE 경기",
      "time": "",
      "color": "#FFC857",
      "link": ""
    }
  ],
  "18": [
    {
      "title": "레이튼 이상한 마을",
      "time": "",
      "color": "#FFC857",
      "link": ""
    }
  ],
  "19": [
    {
      "title": "레이튼 이상한 마을",
      "time": "",
      "color": "#FFC857",
      "link": ""
    }
  ],
  "20": [
    {
      "title": "스타 II Wardi 팀리그",
      "time": "10PM",
      "color": "#34F5D8",
      "link": ""
    },
    {
      "title": "ONSYDE 경기",
      "time": "",
      "color": "#FFC857",
      "link": ""
    }
  ],
  "21": [
    {
      "title": "휴방",
      "time": "",
      "color": "#FF4D6D",
      "link": ""
    }
  ],
  "22": [
    {
      "title": "역사 얘기, 스타 II, 유로트럭",
      "time": "",
      "color": "#34F5D8",
      "link": ""
    },
    {
      "title": "올리비아 여행 컴백",
      "time": "",
      "color": "#FFC857",
      "link": ""
    }
  ],
  "23": [
    {
      "title": "롤",
      "time": "",
      "color": "#FFC857",
      "link": ""
    }
  ],
  "24": [
    {
      "title": "서울 출장 휴방",
      "time": "",
      "color": "#FF4D6D",
      "link": ""
    },
    {
      "title": "새벽에 잠깐 롤",
      "time": "",
      "color": "#FFC857",
      "link": ""
    }
  ],
  "25": [
    {
      "title": "활협전, 레데리 2,",
      "time": "",
      "color": "#FFC857",
      "link": ""
    },
    {
      "title": "피의 거짓, 포켓몬스터 블루",
      "time": "",
      "color": "#FFC857",
      "link": ""
    }
  ],
  "26": [
    {
      "title": "활협전",
      "time": "",
      "color": "#FFC857",
      "link": ""
    },
    {
      "title": "스타 II Wardi 팀리그",
      "time": "10PM",
      "color": "#34F5D8",
      "link": ""
    }
  ],
  "27": [
    {
      "title": "스타 II Wardi 팀리그",
      "time": "12AM",
      "color": "#34F5D8",
      "link": ""
    }
  ],
  "28": [
    {
      "title": "스타 II Wardi 팀리그",
      "time": "11PM",
      "color": "#34F5D8",
      "link": ""
    },
    {
      "title": "ONSYDE 경기",
      "time": "",
      "color": "#FFC857",
      "link": ""
    }
  ],
  "29": [
    {
      "title": "스타 II Wardi 팀리그",
      "time": "11PM",
      "color": "#34F5D8",
      "link": ""
    }
  ],
  "30": [
    {
      "title": "롤",
      "time": "",
      "color": "#FFC857",
      "link": ""
    }
  ],
  "31": [
    {
      "title": "스타 II Wardi 팀리그",
      "time": "10PM",
      "color": "#34F5D8",
      "link": ""
    },
    {
      "title": "ONSYDE 경기",
      "time": "",
      "color": "#FFC857",
      "link": ""
    }
  ]
}